{
  "id": "level52",
  "number": 52,
  "name": "Kestrel",
  "grid": {
    "width": 19,
    "height": 19
  },
  "timeLimit": 18,
  "nodes": [
    {
      "id": 1,
      "position": {
        "x": 13,
        "y": 17
      },
      "neighbors": [
        2,
        6,
        8,
        10
      ]
    },
    {
      "id": 2,
      "position": {
        "x": 1,
        "y": 13
      },
      "neighbors": [
        5,
        10
      ]
    },
    {
      "id": 3,
      "position": {
        "x": 5,
        "y": 1
      },
      "neighbors": []
    },
    {
      "id": 4,
      "position": {
        "x": 13,
        "y": 9
      },
      "neighbors": [
        9
      ]
    },
    {
      "id": 5,
      "position": {
        "x": 1,
        "y": 9
      },
      "neighbors": [
        3,
        9
      ]
    },
    {
      "id": 6,
      "position": {
        "x": 17,
        "y": 13
      },
      "neighbors": [
        7
      ]
    },
    {
      "id": 7,
      "position": {
        "x": 5,
        "y": 9
      },
      "neighbors": []
    },
    {
      "id": 8,
      "position": {
        "x": 17,
        "y": 17
      },
      "neighbors": [
        10
      ]
    },
    {
      "id": 9,
      "position": {
        "x": 1,
        "y": 1
      },
      "neighbors": []
    },
    {
      "id": 10,
      "position": {
        "x": 9,
        "y": 9
      },
      "neighbors": [
        3,
        4,
        9
      ]
    }
  ]
}
